action_graph/__init__.py
action_graph/action.py
action_graph/agent.py
action_graph/planner.py
action_graph-1.3.5.dist-info/WHEEL
action_graph-1.3.5.dist-info/METADATA
action_graph-1.3.5.dist-info/licenses/LICENSE
action_graph-1.3.5.dist-info/RECORD
