Metadata-Version: 2.1
Name: action_graph
Version: 1.3.5
Summary: Autonomous agent for task/action planning and execution
Author-email: Bharath Achyutha Rao <bharath.rao@hotmail.com>
Requires-Python: >=3.7,<4.0
Classifier: License :: OSI Approved :: MIT License
Classifier: Operating System :: OS Independent
Classifier: Programming Language :: Python :: 3
Project-URL: Bug Tracker, https://github.com/bharathra/action_graph/issues
Project-URL: Homepage, https://github.com/bharathra/action_graph
